anomalytics/__init__.py
anomalytics/evals/__init__.py
anomalytics/evals/kolmogorv_smirnov.py
anomalytics/evals/qq_plot.py
anomalytics/models/__init__.py
anomalytics/models/abstract.py
anomalytics/models/autoencoder.py
anomalytics/models/block_maxima.py
anomalytics/models/dbscan.py
anomalytics/models/detector.py
anomalytics/models/isoforest.py
anomalytics/models/mad.py
anomalytics/models/one_class_svm.py
anomalytics/models/peaks_over_threshold.py
anomalytics/models/zscore.py
anomalytics/notifications/__init__.py
anomalytics/notifications/abstract.py
anomalytics/notifications/email.py
anomalytics/notifications/notification.py
anomalytics/notifications/slack.py
anomalytics/plots/__init__.py
anomalytics/plots/hist.py
anomalytics/plots/line.py
anomalytics/plots/plot.py
anomalytics/stats/__init__.py
anomalytics/stats/peaks_over_threshold.py
anomalytics/time_series/__init__.py
anomalytics/time_series/upload.py
anomalytics/time_windows/__init__.py
anomalytics/time_windows/pot_window.py
anomalytics/time_windows/time_window.py
anomalytics-0.2.2.dist-info/LICENSE
anomalytics-0.2.2.dist-info/METADATA
anomalytics-0.2.2.dist-info/WHEEL
anomalytics-0.2.2.dist-info/top_level.txt
anomalytics-0.2.2.dist-info/RECORD
