Metadata-Version: 2.1
Name: anomalytics
Version: 0.2.2
Summary: The ultimate anomaly detection library.
Author-email: Nino Lindenberg <aeternalisingenium@proton.me>
License: MIT License
Project-URL: repository, https://github.com/Aeternalis-Ingenium/anomalytics
Project-URL: documentation, https://github.com/Aeternalis-Ingenium/anomalytics/blob/trunk/README.md
Keywords: anomaly,anomaly detection,statistics,mathematics,software engineering,data science,data analyst
Classifier: Development Status :: 4 - Beta
Classifier: Intended Audience :: Education
Classifier: Intended Audience :: Developers
Classifier: Intended Audience :: Science/Research
Classifier: Natural Language :: English
Classifier: Operating System :: OS Independent
Classifier: Programming Language :: Python :: 3
Classifier: Programming Language :: Python :: 3 :: Only
Classifier: Programming Language :: Python :: 3.9
Classifier: Programming Language :: Python :: 3.10
Classifier: Programming Language :: Python :: 3.11
Classifier: Programming Language :: Python :: 3.12
Classifier: Topic :: Scientific/Engineering :: Mathematics
Classifier: Topic :: Scientific/Engineering
Classifier: Topic :: Software Development :: Libraries
Requires-Python: >=3.10
License-File: LICENSE
Requires-Dist: matplotlib >=3.7.2
Requires-Dist: numpy >=1.25.2
Requires-Dist: pandas >=2.0.3
Requires-Dist: scipy >=1.10.4
Provides-Extra: codequality
Requires-Dist: black >=23.11.0 ; extra == 'codequality'
Requires-Dist: colorama >=0.4.6 ; extra == 'codequality'
Requires-Dist: isort >=5.12.0 ; extra == 'codequality'
Requires-Dist: mypy >=1.7.1 ; extra == 'codequality'
Requires-Dist: pre-commit >=3.5.0 ; extra == 'codequality'
Provides-Extra: docs
Requires-Dist: sphinx >=7.2.6 ; extra == 'docs'
Requires-Dist: sphinx-rtd-theme >=2.0.0 ; extra == 'docs'
Provides-Extra: extra
Requires-Dist: openpyxl ; extra == 'extra'
Provides-Extra: security
Requires-Dist: bandit >=1.7.5 ; extra == 'security'
Provides-Extra: testcov
Requires-Dist: pytest-cov >=4.1.0 ; extra == 'testcov'
